groot_rocker_extensions/__init__.py
groot_rocker_extensions/bind.py
groot_rocker_extensions/colcon.py
groot_rocker_extensions/development_environment.py
groot_rocker_extensions/git.py
groot_rocker_extensions/main.py
groot_rocker_extensions/named_prompt.py
groot_rocker_extensions/nvidia.py
groot_rocker_extensions/pulse_audio.py
groot_rocker_extensions/snorriheim.py
groot_rocker_extensions/ssh.py
groot_rocker_extensions/user.py
groot_rocker_extensions/work_directory.py
groot_rocker_extensions/templates/colcon.Dockerfile.em
groot_rocker_extensions/templates/colcon_setup.bash
groot_rocker_extensions/templates/development_environment.Dockerfile.em
groot_rocker_extensions/templates/named_prompt.Dockerfile.em
groot_rocker_extensions/templates/nvidia_preamble.Dockerfile.em
groot_rocker_extensions/templates/nvidia_snippet.Dockerfile.em
groot_rocker_extensions/templates/pulse_audio_snippet.Dockerfile.em
groot_rocker_extensions/templates/ssh.Dockerfile.em
groot_rocker_extensions/templates/user.Dockerfile.em
groot_rocker_extensions/templates/work_directory.Dockerfile.em
test/__init__.py
test/test_bind.py
test/test_colcon.py
test/test_git.py
test/test_named_prompt.py
test/test_nvidia.py
test/test_pulse_audio.py
test/test_ssh.py
test/test_user.py
test/test_work_directory.py
test/utilities.py
groot_rocker_extensions-0.4.1.dist-info/LICENSE
groot_rocker_extensions-0.4.1.dist-info/METADATA
groot_rocker_extensions-0.4.1.dist-info/WHEEL
groot_rocker_extensions-0.4.1.dist-info/entry_points.txt
groot_rocker_extensions-0.4.1.dist-info/top_level.txt
groot_rocker_extensions-0.4.1.dist-info/RECORD
