Metadata-Version: 2.1
Name: groot-rocker-extensions
Version: 0.4.1
Summary: groot_rocker extensions for groot workflows
Home-page: http://github.com/stonier/groot_rocker_extensions
Author: Daniel Stonier
Maintainer: Daniel Stonier <d.stonier@gmail.com>
License: BSD
Keywords: Docker
Platform: UNKNOWN
Classifier: Environment :: Console
Classifier: Intended Audience :: Developers
Classifier: License :: OSI Approved :: BSD License
Classifier: Programming Language :: Python
Classifier: Programming Language :: Python :: 3
Classifier: Topic :: Software Development :: Libraries
Requires-Python: >=3.0
Requires-Dist: distro
Requires-Dist: groot-rocker
Requires-Dist: setuptools
Provides-Extra: packaging
Requires-Dist: stdeb ; extra == 'packaging'
Requires-Dist: twine ; extra == 'packaging'
Provides-Extra: tests
Requires-Dist: codecov ; extra == 'tests'
Requires-Dist: coverage ; extra == 'tests'
Requires-Dist: nose ; extra == 'tests'
Requires-Dist: pytest ; extra == 'tests'
